torchtime/__init__.py
torchtime/collate.py
torchtime/constants.py
torchtime/data.py
torchtime/impute.py
torchtime/utils.py
torchtime-0.6.1.dist-info/LICENSE
torchtime-0.6.1.dist-info/METADATA
torchtime-0.6.1.dist-info/WHEEL
torchtime-0.6.1.dist-info/RECORD
