Metadata-Version: 2.1
Name: torchtime
Version: 0.6.1
Summary: Benchmark time series data sets for PyTorch
Home-page: https://philipdarke.com/torchtime
License: MIT
Author: Philip Darke
Author-email: hello@philipdarke.com
Requires-Python: >=3.8.1,<3.12
Classifier: License :: OSI Approved :: MIT License
Classifier: Programming Language :: Python :: 3
Classifier: Programming Language :: Python :: 3.9
Classifier: Programming Language :: Python :: 3.10
Classifier: Programming Language :: Python :: 3.11
Requires-Dist: numpy (>=1.21,<2.0)
Requires-Dist: requests (>=2.27.1,<3.0.0)
Requires-Dist: scikit-learn (>=1.1,<2.0)
Requires-Dist: sktime (>=0.17,<0.19)
Requires-Dist: torch (>=1.12,<2.1)
Requires-Dist: tqdm (>=4.64.0,<5.0.0)
Project-URL: Documentation, https://philipdarke.com/torchtime
Project-URL: Repository, https://github.com/philipdarke/torchtime
